declair/__init__.py
declair/const.py
declair/env.py
declair/exception.py
declair/execution.py
declair/helpers.py
declair/results.py
declair/serialization.py
declair/analysis/__init__.py
declair/analysis/functional.py
declair/analysis/ipython_snippet.py
declair/analysis/parse.py
declair/bin/__init__.py
declair/bin/declair_execute.py
declair/bin/declair_omniboard.py
declair/extend/__init__.py
declair/extend/execute.py
declair/extend/insertion.py
declair/extend/special_entries.py
declair/frameworks/__init__.py
declair/frameworks/ignite/__init__.py
declair/frameworks/ignite/data.py
declair/frameworks/ignite/evaluators.py
declair/frameworks/ignite/gpu.py
declair/frameworks/ignite/transforms.py
declair/run/__init__.py
declair/run/call.py
declair/run/env.py
declair/run/execute.py
declair/run/insertion.py
declair/run/sources.py
declair/run/special_entries.py
declair/run/type.py
declair/run/variables.py
declair/search/__init__.py
declair/search/const.py
declair/search/execute.py
declair/search/grid.py
declair/search/hyperopt.py
declair/search/search_info.py
declair/search/special_entries.py
tests/sample/__init__.py
tests/sample/functions.py
tests/sample/placeholders.py
tests/sample/frameworks/__init__.py
tests/sample/frameworks/ignite/__init__.py
tests/sample/frameworks/ignite/data.py
tests/sample/frameworks/ignite/evaluate.py
tests/sample/frameworks/ignite/execute.py
tests/sample/frameworks/ignite/models.py
tests/sample/nested_subpackage/__init__.py
tests/sample/nested_subpackage/some_module.py
declair-0.1.5.dist-info/COPYING
declair-0.1.5.dist-info/METADATA
declair-0.1.5.dist-info/WHEEL
declair-0.1.5.dist-info/entry_points.txt
declair-0.1.5.dist-info/top_level.txt
declair-0.1.5.dist-info/RECORD
