Metadata-Version: 2.1
Name: declair
Version: 0.1.5
Summary: Package for declarative hyperparameter search experiments.
Home-page: https://gitlab.com/k-cybulski/declair
Author: Krzysztof Cybulski
Author-email: declair@kcyb.eu
License: EUPL-1.2-or-later
Platform: UNKNOWN
Requires-Python: >=3.5
License-File: COPYING
Requires-Dist: sacred (>=0.8.2)
Requires-Dist: hyperopt (>=0.2.4)
Requires-Dist: pymongo
Requires-Dist: pyyaml
Requires-Dist: tblib
Requires-Dist: GitPython
Requires-Dist: wrapt
